LICENSE
drf_rockstar_extensions/__init__.py
drf_rockstar_extensions/fields/__init__.py
drf_rockstar_extensions/fields/fetcher_field/__init__.py
drf_rockstar_extensions/fields/fetcher_field/attributes.py
drf_rockstar_extensions/fields/fetcher_field/auths.py
drf_rockstar_extensions/fields/fetcher_field/fetcher_field.py
drf_rockstar_extensions/settings.py
drf_rockstar_extensions-0.0.4.dist-info/LICENSE
drf_rockstar_extensions-0.0.4.dist-info/WHEEL
drf_rockstar_extensions-0.0.4.dist-info/METADATA
drf_rockstar_extensions-0.0.4.dist-info/RECORD
