Metadata-Version: 2.1
Name: drf-rockstar-extensions
Version: 0.0.4
Summary: Extensions that help your project become rockstar
Home-page: https://drf-rockstar-extensions.readthedocs.io
License: MIT
Author: Agung Yuliyanto
Author-email: agung.96tm@gmail.com
Requires-Python: >=3.8,<4.0
Classifier: License :: OSI Approved :: MIT License
Classifier: Programming Language :: Python :: 3
Classifier: Programming Language :: Python :: 3.10
Classifier: Programming Language :: Python :: 3.8
Classifier: Programming Language :: Python :: 3.9
Provides-Extra: docs
Provides-Extra: test
Requires-Dist: djangorestframework (>=3.13.0,<4.0.0)
Requires-Dist: requests (>=2.26.0,<3.0.0)
Project-URL: Documentation, https://drf-rockstar-extensions.readthedocs.io
Project-URL: Repository, https://github.com/agung96tm/drf_rockstar_extensions
